ciscocucmapi/__init__.py
ciscocucmapi/_internal_utils.py
ciscocucmapi/connectors.py
ciscocucmapi/definitions.py
ciscocucmapi/exceptions.py
ciscocucmapi/helpers.py
ciscocucmapi/sql_utils.py
ciscocucmapi/api/__init__.py
ciscocucmapi/api/advanced.py
ciscocucmapi/api/base.py
ciscocucmapi/api/device.py
ciscocucmapi/api/dialplan.py
ciscocucmapi/api/media.py
ciscocucmapi/api/serviceability.py
ciscocucmapi/api/system.py
ciscocucmapi/api/user.py
ciscocucmapi/model/__init__.py
ciscocucmapi/model/axldata.py
ciscocucmapi-0.0.2.dist-info/AUTHORS.rst
ciscocucmapi-0.0.2.dist-info/LICENSE
ciscocucmapi-0.0.2.dist-info/METADATA
ciscocucmapi-0.0.2.dist-info/WHEEL
ciscocucmapi-0.0.2.dist-info/entry_points.txt
ciscocucmapi-0.0.2.dist-info/top_level.txt
ciscocucmapi-0.0.2.dist-info/RECORD
