Metadata-Version: 2.1
Name: ciscocucmapi
Version: 0.0.2
Summary: Python Wrappers for Cisco CUCM SOAP APIs
Home-page: https://github.com/jonathanelscpt/ciscocucmapi
Author: Jonathan Els
Author-email: jonathanelscpt@gmail.com
License: MIT
Project-URL: Documentation, https://ciscocucmapi.readthedocs.io/
Project-URL: Changelog, https://ciscocucmapi.readthedocs.io/en/latest/changelog.html
Project-URL: Issue Tracker, https://github.com/jonathanelscpt/ciscocucmapi/issues
Keywords: cisco,cucm,uc,collaboration,callmanager,axl
Platform: UNKNOWN
Classifier: Development Status :: 3 - Alpha
Classifier: Intended Audience :: Developers
Classifier: Intended Audience :: System Administrators
Classifier: Natural Language :: English
Classifier: License :: OSI Approved :: MIT License
Classifier: Operating System :: Unix
Classifier: Operating System :: POSIX
Classifier: Operating System :: Microsoft :: Windows
Classifier: Programming Language :: Python
Classifier: Programming Language :: Python :: 3.6
Classifier: Programming Language :: Python :: 3.7
Classifier: Programming Language :: Python :: 3.8
Classifier: Programming Language :: Python :: Implementation :: CPython
Classifier: Programming Language :: Python :: Implementation :: PyPy
Classifier: Topic :: Communications :: Telephony
Classifier: Topic :: Communications :: Conferencing
Classifier: Topic :: System :: Systems Administration
Classifier: Topic :: Utilities
Requires-Python: >=3.6
Requires-Dist: requests (>=2.18.4)
Requires-Dist: zeep (>=2.5.0)
Provides-Extra: rst
Requires-Dist: docutils (>=0.11) ; extra == 'rst'
